mcp_calpower_server/__init__.py
mcp_calpower_server/server.py
mcp_calpower_server-0.4.0.dist-info/METADATA
mcp_calpower_server-0.4.0.dist-info/WHEEL
mcp_calpower_server-0.4.0.dist-info/entry_points.txt
mcp_calpower_server-0.4.0.dist-info/licenses/LICENSE
mcp_calpower_server-0.4.0.dist-info/RECORD
