Metadata-Version: 2.4
Name: mcp-calpower-server
Version: 0.4.0
Summary: A Model Context Protocol server for power calculating
License-File: LICENSE
Requires-Python: >=3.10
Requires-Dist: mcp>=1.4.1
